[{"id":"FIAT_124","name":"124","class":"C","year-from":1966,"year-to":1976,"generations":[{"id":"10401162","name":"I","year-start":1966,"year-stop":1976}]},{"id":"FIAT_124_SPIDER","name":"124 Spider","class":"S","year-from":2016,"year-to":2020,"generations":[{"id":"20721659","name":"I","year-start":2016,"year-stop":2020}]},{"id":"FIAT_124_SPORT_SPIDER","name":"124 Sport Spider","class":"S","year-from":1966,"year-to":1985,"generations":[{"id":"10401194","name":"I","year-start":1966,"year-stop":1985}]},{"id":"FIAT_125","name":"125","class":"B","year-from":1967,"year-to":1982,"generations":[{"id":"21488302","name":"","year-start":1967,"year-stop":1982}]},{"id":"FIAT_126","name":"126","class":"A","year-from":1972,"year-to":1996,"generations":[{"id":"10401226","name":"I","year-start":1972,"year-stop":1996}]},{"id":"FIAT_127","name":"127","class":"B","year-from":1971,"year-to":1987,"generations":[{"id":"10401247","name":"","year-start":1971,"year-stop":1987}]},{"id":"FIAT_128","name":"128","class":"B","year-from":1969,"year-to":1985,"generations":[{"id":"20346180","name":"","year-start":1969,"year-stop":1985}]},{"id":"FIAT_130","name":"130","class":"D","year-from":1969,"year-to":1978,"generations":[{"id":"20346191","name":"","year-start":1969,"year-stop":1978}]},{"id":"FIAT_131","name":"131","class":"C","year-from":1974,"year-to":1985,"generations":[{"id":"10401262","name":"","year-start":1974,"year-stop":1985}]},{"id":"FIAT_132","name":"132","class":"D","year-from":1972,"year-to":1982,"generations":[{"id":"20346202","name":"","year-start":1972,"year-stop":1982}]},{"id":"FIAT_2300","name":"2300","class":"C","year-from":1961,"year-to":1969,"generations":[{"id":"22619008","name":"","year-start":1961,"year-stop":1969}]},{"id":"FIAT_238","name":"238","class":"M","year-from":1966,"year-to":1982,"generations":[{"id":"20346213","name":"","year-start":1966,"year-stop":1982}]},{"id":"FIAT_500","name":"500","class":"A","year-from":1936,"year-to":null,"generations":[{"id":"23280554","name":"III","year-start":2020,"year-stop":null},{"id":"20640064","name":"II Рестайлинг","year-start":2015,"year-stop":null},{"id":"3652509","name":"II","year-start":2007,"year-stop":2015},{"id":"20335803","name":"I","year-start":1957,"year-stop":1975},{"id":"23922565","name":"Topolino","year-start":1936,"year-stop":1955}]},{"id":"FIAT_500L","name":"500L","class":"M","year-from":2012,"year-to":2022,"generations":[{"id":"21684283","name":"I Рестайлинг","year-start":2017,"year-stop":2022},{"id":"20515630","name":"I","year-start":2012,"year-stop":2017}]},{"id":"FIAT_500X","name":"500X","class":"B","year-from":2014,"year-to":null,"generations":[{"id":"21459515","name":"I Рестайлинг","year-start":2018,"year-stop":null},{"id":"20300221","name":"I","year-start":2014,"year-stop":2018}]},{"id":"FIAT_508","name":"508","class":"","year-from":1932,"year-to":1939,"generations":[{"id":"20725072","name":"","year-start":1932,"year-stop":1939}]},{"id":"FIAT_600","name":"600","class":"B","year-from":2005,"year-to":2010,"generations":[{"id":"3480169","name":"","year-start":2005,"year-stop":2010}]},{"id":"FIAT_600E","name":"600e","class":"B","year-from":2023,"year-to":null,"generations":[{"id":"23648291","name":"","year-start":2023,"year-stop":null}]},{"id":"FIAT_900T","name":"900T","class":"M","year-from":1976,"year-to":1985,"generations":[{"id":"20352161","name":"","year-start":1976,"year-stop":1985}]},{"id":"FIAT_ALBEA","name":"Albea","class":"C","year-from":2002,"year-to":2012,"generations":[{"id":"2306362","name":"I Рестайлинг","year-start":2005,"year-stop":2012},{"id":"4601398","name":"I","year-start":2002,"year-stop":2005}]},{"id":"FIAT_ARGENTA","name":"Argenta","class":"C","year-from":1978,"year-to":1986,"generations":[{"id":"20352150","name":"","year-start":1978,"year-stop":1986}]},{"id":"FIAT_BARCHETTA","name":"Barchetta","class":"C","year-from":1995,"year-to":2005,"generations":[{"id":"4721166","name":"I Рестайлинг","year-start":2003,"year-stop":2005},{"id":"4994951","name":"I","year-start":1995,"year-stop":2003}]},{"id":"FIAT_BRAVA","name":"Brava","class":"C","year-from":1995,"year-to":2001,"generations":[{"id":"4994915","name":"","year-start":1995,"year-stop":2001}]},{"id":"FIAT_BRAVO","name":"Bravo","class":"C","year-from":1995,"year-to":2014,"generations":[{"id":"2306375","name":"II","year-start":2007,"year-stop":2014},{"id":"3475926","name":"I","year-start":1995,"year-stop":2001}]},{"id":"FIAT_CINQUECENTO","name":"Cinquecento","class":"A","year-from":1991,"year-to":1998,"generations":[{"id":"6015981","name":"","year-start":1991,"year-stop":1998}]},{"id":"FIAT_COUPE","name":"Coupe","class":"C","year-from":1993,"year-to":2001,"generations":[{"id":"4994957","name":"","year-start":1993,"year-stop":2001}]},{"id":"FIAT_CROMA","name":"Croma","class":"C","year-from":1985,"year-to":2011,"generations":[{"id":"2306397","name":"II Рестайлинг","year-start":2008,"year-stop":2011},{"id":"3475929","name":"II","year-start":2005,"year-stop":2008},{"id":"3475931","name":"I","year-start":1985,"year-stop":1996}]},{"id":"FIAT_DOBLO","name":"Doblo","class":"M","year-from":2000,"year-to":2022,"generations":[{"id":"20485162","name":"II Рестайлинг","year-start":2015,"year-stop":2022},{"id":"20067130","name":"II","year-start":2009,"year-stop":2015},{"id":"2306411","name":"I Рестайлинг","year-start":2005,"year-stop":2015},{"id":"6448600","name":"I","year-start":2000,"year-stop":2005}]},{"id":"FIAT_DUNA","name":"Duna","class":"B","year-from":1987,"year-to":1991,"generations":[{"id":"20346224","name":"","year-start":1987,"year-stop":1991}]},{"id":"FIAT_EGEA","name":"Egea","class":"C","year-from":2015,"year-to":null,"generations":[{"id":"23414095","name":"I Рестайлинг","year-start":2020,"year-stop":null},{"id":"23410935","name":"I","year-start":2015,"year-stop":2020}]},{"id":"FIAT_FIORINO","name":"Fiorino","class":"B","year-from":1977,"year-to":null,"generations":[{"id":"10401416","name":"III","year-start":2007,"year-stop":null},{"id":"10401401","name":"II","year-start":1987,"year-stop":2013},{"id":"20335824","name":"I","year-start":1977,"year-stop":1987}]},{"id":"FIAT_FREEMONT","name":"Freemont","class":"M","year-from":2011,"year-to":2016,"generations":[{"id":"10385620","name":"","year-start":2011,"year-stop":2016}]},{"id":"FIAT_FULLBACK","name":"Fullback","class":"J","year-from":2016,"year-to":2020,"generations":[{"id":"20805307","name":"I","year-start":2016,"year-stop":2020}]},{"id":"FIAT_IDEA","name":"Idea","class":"M","year-from":2003,"year-to":2016,"generations":[{"id":"2306367","name":"","year-start":2003,"year-stop":2016}]},{"id":"FIAT_LINEA","name":"Linea","class":"C","year-from":2006,"year-to":2018,"generations":[{"id":"2306392","name":"","year-start":2006,"year-stop":2018}]},{"id":"FIAT_MAREA","name":"Marea","class":"C","year-from":1996,"year-to":2002,"generations":[{"id":"4760008","name":"","year-start":1996,"year-stop":2002}]},{"id":"FIAT_MULTIPLA","name":"Multipla","class":"M","year-from":1998,"year-to":2010,"generations":[{"id":"2306406","name":"I Рестайлинг","year-start":2004,"year-stop":2010},{"id":"4841733","name":"I","year-start":1998,"year-stop":2005}]},{"id":"FIAT_PALIO","name":"Palio","class":"B","year-from":1996,"year-to":2017,"generations":[{"id":"6468616","name":"II","year-start":2011,"year-stop":2017},{"id":"4841724","name":"I Рестайлинг","year-start":2001,"year-stop":2004},{"id":"5139829","name":"I","year-start":1996,"year-stop":2001}]},{"id":"FIAT_PANDA","name":"Panda","class":"A","year-from":1981,"year-to":null,"generations":[{"id":"9269125","name":"III","year-start":2011,"year-stop":null},{"id":"2306325","name":"II","year-start":2003,"year-stop":2012},{"id":"3475935","name":"I","year-start":1981,"year-stop":2003}]},{"id":"FIAT_PUNTO","name":"Punto","class":"B","year-from":1993,"year-to":2018,"generations":[{"id":"7951992","name":"III Punto","year-start":2012,"year-stop":2018},{"id":"20355288","name":"III Punto Evo","year-start":2009,"year-stop":2012},{"id":"2306345","name":"III Grande Punto","year-start":2005,"year-stop":2010},{"id":"2306335","name":"II Рестайлинг","year-start":2003,"year-stop":2011},{"id":"3475938","name":"II","year-start":1999,"year-stop":2003},{"id":"3475943","name":"I","year-start":1993,"year-stop":1999}]},{"id":"FIAT_QUBO","name":"Qubo","class":"M","year-from":2007,"year-to":2019,"generations":[{"id":"21008842","name":"I Рестайлинг","year-start":2016,"year-stop":2019},{"id":"20062532","name":"I","year-start":2007,"year-stop":2016}]},{"id":"FIAT_REGATA","name":"Regata","class":"C","year-from":1983,"year-to":1990,"generations":[{"id":"10401671","name":"","year-start":1983,"year-stop":1990}]},{"id":"FIAT_RITMO","name":"Ritmo","class":"C","year-from":1978,"year-to":1989,"generations":[{"id":"20335866","name":"I Рестайлинг","year-start":1982,"year-stop":1988},{"id":"20335845","name":"I","year-start":1978,"year-stop":1989}]},{"id":"FIAT_SCUDO","name":"Scudo","class":"","year-from":1995,"year-to":2016,"generations":[{"id":"20157801","name":"II","year-start":2007,"year-stop":2016},{"id":"20157798","name":"I","year-start":1995,"year-stop":2007}]},{"id":"FIAT_SEDICI","name":"Sedici","class":"C","year-from":2005,"year-to":2014,"generations":[{"id":"2306430","name":"","year-start":2005,"year-stop":2014}]},{"id":"FIAT_SEICENTO","name":"Seicento","class":"A","year-from":1998,"year-to":2010,"generations":[{"id":"6468695","name":"I Рестайлинг","year-start":2005,"year-stop":2010},{"id":"4841708","name":"I","year-start":1998,"year-stop":2005}]},{"id":"FIAT_SIENA","name":"Siena","class":"B","year-from":1996,"year-to":2017,"generations":[{"id":"4994894","name":"","year-start":1996,"year-stop":2017}]},{"id":"FIAT_STILO","name":"Stilo","class":"C","year-from":2001,"year-to":2007,"generations":[{"id":"4721138","name":"","year-start":2001,"year-stop":2007}]},{"id":"FIAT_STRADA","name":"Strada","class":"J","year-from":1998,"year-to":2021,"generations":[{"id":"20346234","name":"","year-start":1998,"year-stop":2021}]},{"id":"FIAT_TEMPRA","name":"Tempra","class":"C","year-from":1990,"year-to":1999,"generations":[{"id":"20346244","name":"","year-start":1990,"year-stop":1999}]},{"id":"FIAT_TIPO","name":"Tipo","class":"C","year-from":1987,"year-to":null,"generations":[{"id":"22992311","name":"356 Рестайлинг","year-start":2020,"year-stop":null},{"id":"20726976","name":"356","year-start":2015,"year-stop":2020},{"id":"10402619","name":"160","year-start":1987,"year-stop":1995}]},{"id":"FIAT_ULYSSE","name":"Ulysse","class":"M","year-from":1994,"year-to":null,"generations":[{"id":"23688070","name":"III","year-start":2022,"year-stop":null},{"id":"2306425","name":"II","year-start":2002,"year-stop":2010},{"id":"6470543","name":"I Рестайлинг","year-start":1998,"year-stop":2002},{"id":"3475947","name":"I","year-start":1994,"year-stop":1998}]},{"id":"FIAT_UNO","name":"Uno","class":"B","year-from":1983,"year-to":2002,"generations":[{"id":"10402272","name":"I Рестайлинг","year-start":1989,"year-stop":2002},{"id":"4994887","name":"I","year-start":1983,"year-stop":1989}]},{"id":"FIAT_X_1_9","name":"X 1/9","class":"S","year-from":1972,"year-to":1982,"generations":[{"id":"20346255","name":"","year-start":1972,"year-stop":1982}]}]