[{"id":"LIFAN_650_EV","name":"650 EV","class":"C","year-from":2018,"year-to":2020,"generations":[{"id":"22480830","name":"","year-start":2018,"year-stop":2020}]},{"id":"LIFAN_BREEZ","name":"Breez (520)","class":"C","year-from":2007,"year-to":2014,"generations":[{"id":"3475062","name":"","year-start":2007,"year-stop":2014}]},{"id":"LIFAN_CEBRIUM","name":"Cebrium (720)","class":"D","year-from":2014,"year-to":2018,"generations":[{"id":"20100938","name":"","year-start":2014,"year-stop":2018}]},{"id":"LIFAN_CELLIYA","name":"Celliya (530)","class":"B","year-from":2014,"year-to":2018,"generations":[{"id":"20152746","name":"","year-start":2014,"year-stop":2018}]},{"id":"LIFAN_MURMAN","name":"Murman (820)","class":"D","year-from":2015,"year-to":2020,"generations":[{"id":"21038321","name":"","year-start":2015,"year-stop":2020}]},{"id":"LIFAN_MYWAY","name":"Myway","class":"C","year-from":2016,"year-to":2020,"generations":[{"id":"20973420","name":"","year-start":2016,"year-stop":2020}]},{"id":"LIFAN_SMILY","name":"Smily","class":"A","year-from":2008,"year-to":2018,"generations":[{"id":"20233057","name":"I Рестайлинг (330)","year-start":2014,"year-stop":2018},{"id":"7163053","name":"I (320)","year-start":2008,"year-stop":2015}]},{"id":"LIFAN_SOLANO","name":"Solano","class":"C","year-from":2008,"year-to":2018,"generations":[{"id":"20845463","name":"II","year-start":2016,"year-stop":2018},{"id":"20233046","name":"I Рестайлинг (630)","year-start":2014,"year-stop":2016},{"id":"6130320","name":"I (620)","year-start":2008,"year-stop":2015}]},{"id":"LIFAN_X50","name":"X50","class":"B","year-from":2015,"year-to":2019,"generations":[{"id":"20593038","name":"","year-start":2015,"year-stop":2019}]},{"id":"LIFAN_X60","name":"X60","class":"C","year-from":2011,"year-to":2018,"generations":[{"id":"20882586","name":"I Рестайлинг 2","year-start":2016,"year-stop":2018},{"id":"20640795","name":"I Рестайлинг","year-start":2015,"year-stop":2016},{"id":"8485989","name":"I","year-start":2011,"year-stop":2015}]},{"id":"LIFAN_X70","name":"X70","class":"C","year-from":2017,"year-to":2020,"generations":[{"id":"21251497","name":"I","year-start":2017,"year-stop":2020}]}]