[{"id":"ZEEKR_001","name":"001","class":"E","year-from":2021,"year-to":null,"generations":[{"id":"23888277","name":"I Рестайлинг","year-start":2023,"year-stop":null},{"id":"23280062","name":"I","year-start":2021,"year-stop":null}]},{"id":"ZEEKR_007","name":"007","class":"D","year-from":2023,"year-to":null,"generations":[{"id":"23784636","name":"","year-start":2023,"year-stop":null}]},{"id":"ZEEKR_009","name":"009","class":"M","year-from":2022,"year-to":null,"generations":[{"id":"23411242","name":"","year-start":2022,"year-stop":null}]},{"id":"ZEEKR_X","name":"X","class":"C","year-from":2023,"year-to":null,"generations":[{"id":"23566960","name":"","year-start":2023,"year-stop":null}]}]