[{"id":"ZOTYE_COUPA","name":"Coupa","class":"D","year-from":2018,"year-to":null,"generations":[{"id":"21383949","name":"","year-start":2018,"year-stop":null}]},{"id":"ZOTYE_DOMY_X7","name":"Domy X7","class":"D","year-from":2017,"year-to":2018,"generations":[{"id":"23987611","name":"","year-start":2017,"year-stop":2018}]},{"id":"ZOTYE_E200","name":"E200","class":"A","year-from":2016,"year-to":2021,"generations":[{"id":"22525526","name":"","year-start":2016,"year-stop":2021}]},{"id":"ZOTYE_NOMAD","name":"Nomad (RX6400)","class":"B","year-from":2005,"year-to":2016,"generations":[{"id":"20351629","name":"","year-start":2005,"year-stop":2016}]},{"id":"ZOTYE_SR9","name":"SR9","class":"D","year-from":2016,"year-to":2019,"generations":[{"id":"20909778","name":"I","year-start":2016,"year-stop":2019}]},{"id":"ZOTYE_T300","name":"T300","class":"C","year-from":2017,"year-to":null,"generations":[{"id":"23940900","name":"","year-start":2017,"year-stop":null}]},{"id":"ZOTYE_T600","name":"T600","class":"D","year-from":2013,"year-to":2021,"generations":[{"id":"20670444","name":"","year-start":2013,"year-stop":2021}]},{"id":"ZOTYE_Z100","name":"Z100","class":"A","year-from":2013,"year-to":2017,"generations":[{"id":"20738210","name":"","year-start":2013,"year-stop":2017}]},{"id":"ZOTYE_Z300","name":"Z300","class":"C","year-from":2012,"year-to":2017,"generations":[{"id":"20670255","name":"","year-start":2012,"year-stop":2017}]}]